{"_ts":[1561957857],"_r":{"breakdown":{"html":{"bytes":[37556],"requests":[3]},"js":{"bytes":[200574],"requests":[20]},"css":{"bytes":[60497],"requests":[20]},"image":{"bytes":[19884],"requests":[12]},"flash":{"bytes":[0],"requests":[0]},"font":{"bytes":[447645],"requests":[4]},"video":{"bytes":[0],"requests":[0]},"other":{"bytes":[835],"requests":[4]}},"date":[1561957857],"domElements":[3252],"domInteractive":[10798],"firstPaint":[10670.2000000005],"fullyLoaded":[12486],"id":["190701_33_074a6934a672a4eef55e4dc6a8005cee"],"loadTime":[11649],"render":[10700],"SpeedIndex":[10706],"TTFB":[9616],"videoFrames":[[{"_i":"ms_000000.jpg","_t":0,"_vc":0},{"_i":"ms_010700.jpg","_t":10700,"_vc":98},{"_i":"ms_010800.jpg","_t":10800,"_vc":99},{"_i":"ms_010900.jpg","_t":10900,"_vc":99},{"_i":"ms_011200.jpg","_t":11200,"_vc":100}]],"visualComplete":[11200],"lighthouse":[31],"pagespeed":[82]}}